setup.py
test/test_ymlconfig.py
ymlconfig/Preprocessor.py
ymlconfig/__init__.py
ymlconfig.egg-info/PKG-INFO
ymlconfig.egg-info/SOURCES.txt
ymlconfig.egg-info/dependency_links.txt
ymlconfig.egg-info/not-zip-safe
ymlconfig.egg-info/requires.txt
ymlconfig.egg-info/top_level.txt