Metadata-Version: 1.1
Name: ymlconfig
Version: 0.2.0
Summary: yaml configuration file support
Home-page: https://github.com/efwahl/ymlconfig
Author: Edward F. Wahl
Author-email: efwahl@gyre.biz
License: MIT
Platform: UNKNOWN
Classifier: Programming Language :: Python
Classifier: Programming Language :: Python :: 3
Classifier: Development Status :: 4 - Beta
Classifier: Intended Audience :: Developers
Classifier: License :: OSI Approved :: MIT License
Classifier: Operating System :: OS Independent
Classifier: Topic :: Software Development :: Libraries :: Python Modules
